acex_cli/__init__.py
acex_cli/commands/__init__.py
acex_cli/commands/asset.py
acex_cli/commands/context.py
acex_cli/commands/node.py
acex_cli/context.py
acex_cli/main.py
acex_cli/print_utils.py
acex_cli/sdk.py
acex_cli-0.2.4.dist-info/METADATA
acex_cli-0.2.4.dist-info/WHEEL
acex_cli-0.2.4.dist-info/entry_points.txt
acex_cli-0.2.4.dist-info/RECORD
