Metadata-Version: 2.4
Name: acex-cli
Version: 0.2.4
Summary: ACE-X CLI - Command-line interface for ACE-X
License: AGPL-3.0
Keywords: automation,cli,control
Author: Johan Lahti
Author-email: johan.lahti@acebit.se
Requires-Python: >=3.13,<4.0
Classifier: License :: OSI Approved :: GNU Affero General Public License v3
Classifier: Programming Language :: Python :: 3
Classifier: Programming Language :: Python :: 3.13
Classifier: Programming Language :: Python :: 3.14
Requires-Dist: acex-client (>=0.2.4,<0.3.0)
Requires-Dist: click (==8.1.7)
Requires-Dist: rich (>=13.0.0,<14.0.0)
Requires-Dist: typer (>=0.12.0,<0.13.0)
Project-URL: Homepage, https://github.com/acex-labs/acex
Project-URL: Repository, https://github.com/acex-labs/acex
